agent_build_refactored/__init__.py
agent_build_refactored/prepare_agent_filesystem.py
agent_build_refactored/container_images/__init__.py
agent_build_refactored/container_images/fips_image_builders.py
agent_build_refactored/container_images/image_builders.py
agent_build_refactored/managed_packages/__init__.py
agent_build_refactored/managed_packages/managed_packages_builders.py
agent_build_refactored/managed_packages/dependencies/__init__.py
agent_build_refactored/utils/__init__.py
agent_build_refactored/utils/builder.py
agent_build_refactored/utils/common.py
agent_build_refactored/utils/constants.py
agent_build_refactored/utils/aws/__init__.py
agent_build_refactored/utils/aws/ami.py
agent_build_refactored/utils/aws/common.py
agent_build_refactored/utils/aws/ec2.py
agent_build_refactored/utils/toolset_image/__init__.py
benchmarks/__init__.py
benchmarks/micro/__init__.py
benchmarks/micro/conftest.py
benchmarks/micro/test_add_events_request_serialization.py
benchmarks/micro/test_calculate_hash_digest.py
benchmarks/micro/test_compression_algorithms.py
benchmarks/micro/test_date_parsing.py
benchmarks/micro/test_event_serialization.py
benchmarks/micro/test_json_serialization.py
benchmarks/micro/test_syslog_parsing.py
benchmarks/micro/time_utils.py
benchmarks/micro/utils.py
pylint_plugins/__init__.py
pylint_plugins/bundled_imports_checker.py
pylint_plugins/py2exe_checker.py
pylint_plugins/windows_monitors_import_checker.py
scalyr_agent/VERSION
scalyr_agent/__init__.py
scalyr_agent/__scalyr__.py
scalyr_agent/agent_main.py
scalyr_agent/agent_status.py
scalyr_agent/all_tests.py
scalyr_agent/build_info.py
scalyr_agent/compat.py
scalyr_agent/config_main.py
scalyr_agent/config_util.py
scalyr_agent/configuration.py
scalyr_agent/connection.py
scalyr_agent/date_parsing_utils.py
scalyr_agent/line_matcher.py
scalyr_agent/log_processing.py
scalyr_agent/log_watcher.py
scalyr_agent/monitors_manager.py
scalyr_agent/platform_controller.py
scalyr_agent/platform_linux.py
scalyr_agent_2-2.2.8.dist-info/LICENSE.txt
scalyr_agent_2-2.2.8.dist-info/METADATA
scalyr_agent_2-2.2.8.dist-info/NOTICE.md
scalyr_agent_2-2.2.8.dist-info/WHEEL
scalyr_agent_2-2.2.8.dist-info/top_level.txt
scalyr_agent_2-2.2.8.dist-info/RECORD
