Metadata-Version: 2.1
Name: scalyr-agent-2
Version: 2.2.8
Summary: The Python modules that implements Scalyr Agent 2
Home-page: https://www.scalyr.com/help/scalyr-agent-2
Author: Scalyr, Inc
Author-email: contact@scalyr.com
License: Apache
Keywords: monitoring tools
Platform: UNKNOWN
Classifier: Development Status :: 5 - Production/Stable
Classifier: Intended Audience :: System Administrators
Classifier: Topic :: System :: Logging
Classifier: Topic :: System :: Monitoring
Classifier: License :: OSI Approved :: Apache Software License
Classifier: Programming Language :: Python :: 2
Classifier: Programming Language :: Python :: 2.6
Classifier: Programming Language :: Python :: 2.7
Classifier: Programming Language :: Python :: 3
Classifier: Programming Language :: Python :: 3.5
Classifier: Programming Language :: Python :: 3.6
Classifier: Programming Language :: Python :: 3.7
Classifier: Programming Language :: Python :: 3.8
Classifier: Programming Language :: Python :: 3.9
Classifier: Programming Language :: Python :: 3.10
Classifier: Programming Language :: Python :: Implementation :: CPython
Classifier: Programming Language :: Python :: Implementation :: PyPy
